{
  "phase": "P100",
  "final_classification": "P100_WAIT_STATE_NOOP_CONFIRMED",
  "classification_rationale": "No new data since P99 (delta_outcome=0, delta_canonical=0). schedule_coverage_pct=34.0741% (threshold: 60.0%). observed_months=3 (threshold: 4). No-op confirmed. Agent should NOT run any new phase today. Await new 2026 outcome rows.",
  "allowed_classifications": [
    "P100_WAIT_STATE_NOOP_CONFIRMED",
    "P100_WAIT_STATE_UPDATED_SNAPSHOT_REQUIRED",
    "P100_READY_FOR_CEO_RERUN_AUTHORIZATION",
    "P100_WAIT_STATE_NOOP_FAILED_VALIDATION"
  ],
  "date": "2026-05-29",
  "generated_at": "2026-05-28T11:43:08.697162Z",
  "git_head": "4b62513",
  "step1_upstream_verification": {
    "step": "step1_upstream_verification",
    "all_gates_ok": true,
    "gates_passed": [
      "P99_file_exists",
      "P98_file_exists",
      "P97_file_exists",
      "P96_file_exists",
      "P95_file_exists",
      "P94_file_exists",
      "P84E_file_exists",
      "P99_classification_ok",
      "P98_classification_ok",
      "P97_classification_ok",
      "P96_classification_ok",
      "P95_classification_ok",
      "P94_classification_ok",
      "P99_p96_rerun_ready_false",
      "P99_ingestion_readiness_ok",
      "P99_governance_flags_clean"
    ],
    "failures": []
  },
  "step2_data_recount": {
    "step": "step2_data_recount",
    "schedule_rows": 2430,
    "total_canonical_rows": 828,
    "outcome_available_rows": 808,
    "rows_with_sp_fip_delta": 808,
    "high_fip_rows": 287,
    "mid_fip_rows": 343,
    "low_fip_rows": 178,
    "observed_months": [
      "2026-03",
      "2026-04",
      "2026-05"
    ],
    "n_observed_months": 3,
    "date_range": {
      "min": "2026-03-25",
      "max": "2026-05-31"
    },
    "schedule_coverage_pct": 34.0741,
    "outcome_coverage_pct": 33.251,
    "p99_baseline_comparison": {
      "p99_baseline_canonical_rows": 828,
      "p99_baseline_outcome_rows": 808,
      "p99_baseline_high_fip_n": 287,
      "p99_baseline_mid_fip_n": 343,
      "p99_baseline_low_fip_n": 178,
      "p99_baseline_coverage_pct": 34.0741,
      "p99_baseline_observed_months": 3,
      "delta_canonical_rows": 0,
      "delta_outcome_rows": 0,
      "delta_high_fip_rows": 0,
      "delta_mid_fip_rows": 0,
      "delta_low_fip_rows": 0,
      "delta_observed_months": 0,
      "delta_schedule_coverage_pct": 0.0
    },
    "status": "PASSED"
  },
  "step3_noop_decision": {
    "step": "step3_noop_decision",
    "noop_state": "NOOP_CONFIRMED",
    "delta_outcome_rows": 0,
    "delta_high_fip_rows": 0,
    "schedule_coverage_pct": 34.0741,
    "observed_months": 3,
    "above_coverage_threshold": false,
    "above_months_threshold": false,
    "no_new_data": true,
    "new_data_exists": false,
    "ceo_gate_triggered": false,
    "thresholds": {
      "coverage_pct": {
        "required": 60.0,
        "current": 34.0741,
        "status": "WAIT"
      },
      "observed_months": {
        "required": 4,
        "current": 3,
        "status": "WAIT"
      }
    },
    "status": "PASSED"
  },
  "step4_wait_state_instruction": {
    "step": "step4_wait_state_instruction",
    "noop_state": "NOOP_CONFIRMED",
    "action": "DO_NOT_RUN_NEW_PHASE",
    "reason": "NO_NEW_DATA_AND_THRESHOLDS_NOT_MET",
    "recommended_next": "wait for new 2026 outcomes",
    "next_check_trigger": {
      "trigger_1": "delta_outcome_rows > 0 (new outcome rows have arrived)",
      "trigger_2": "schedule_coverage_pct >= 60.0 (currently 34.0741%)",
      "trigger_3": "observed_months >= 4 (currently 3)",
      "trigger_4": "explicit CEO authorization for P96 rerun"
    },
    "allowed_next_actions": [
      {
        "action": "wait_for_new_2026_outcomes",
        "description": "No active work. Wait for 2026 season games to complete and produce new outcome rows.",
        "safe": true
      },
      {
        "action": "monitor_schedule_coverage",
        "description": "Passively monitor schedule_coverage_pct. No action until thresholds trigger.",
        "safe": true
      },
      {
        "action": "rerun_p99_when_new_outcomes_arrive",
        "description": "Rerun P99 snapshot check when delta_outcome_rows > 0. Compare baseline vs P99.",
        "safe": true
      },
      {
        "action": "rerun_p100_to_confirm_noop",
        "description": "Rerun P100 no-op guard periodically to confirm wait-state is still valid.",
        "safe": true
      },
      {
        "action": "request_ceo_authorization_when_thresholds_met",
        "description": "Request CEO authorization for P96 rerun ONLY when schedule_coverage_pct >= 60 AND observed_months >= 4. Do not proceed without authorization.",
        "safe": true
      }
    ],
    "prohibited_next_actions": [
      {
        "action": "production_promotion",
        "reason": "production_governance_gate=FAIL in P97. CEO authorization required."
      },
      {
        "action": "recommendation_surface",
        "reason": "recommendation_contract_gate=FAIL in P97. No paper rec contract."
      },
      {
        "action": "odds_integration",
        "reason": "odds_dataset_gate=FAIL in P97. No legal odds dataset."
      },
      {
        "action": "ev_clv_kelly_computation",
        "reason": "market_edge_gate=FAIL in P97. No legal odds data."
      },
      {
        "action": "calibration_refit",
        "reason": "calibration_gate=FAIL in P97. No refit authorized."
      },
      {
        "action": "champion_replacement",
        "reason": "production_governance_gate=FAIL in P97. No champion mutation."
      },
      {
        "action": "taiwan_lottery_paper_recommendation",
        "reason": "recommendation_allowed=false. governance lock."
      },
      {
        "action": "stake_sizing",
        "reason": "risk_control_gate=FAIL in P97. Kelly not computed."
      },
      {
        "action": "rerun_p96_before_thresholds",
        "reason": "Premature rerun wastes diagnostic credibility; wait for thresholds."
      },
      {
        "action": "rerun_p97_before_thresholds",
        "reason": "Premature rerun wastes diagnostic credibility; wait for thresholds."
      }
    ],
    "status": "PASSED"
  },
  "step5_final_classification": {
    "step": "step5_final_classification",
    "final_classification": "P100_WAIT_STATE_NOOP_CONFIRMED",
    "rationale": "No new data since P99 (delta_outcome=0, delta_canonical=0). schedule_coverage_pct=34.0741% (threshold: 60.0%). observed_months=3 (threshold: 4). No-op confirmed. Agent should NOT run any new phase today. Await new 2026 outcome rows.",
    "noop_state": "NOOP_CONFIRMED",
    "action": "DO_NOT_RUN_NEW_PHASE",
    "reason": "NO_NEW_DATA_AND_THRESHOLDS_NOT_MET",
    "schedule_coverage_pct": 34.0741,
    "observed_months": 3,
    "delta_outcome_rows": 0
  },
  "governance_guards": {
    "paper_only": true,
    "diagnostic_only": true,
    "production_ready": false,
    "real_bet_allowed": false,
    "recommendation_allowed": false,
    "product_surface_allowed": false,
    "odds_used": false,
    "ev_computed": false,
    "clv_computed": false,
    "kelly_computed": false,
    "stake_sizing": false,
    "taiwan_lottery_recommendation": false,
    "champion_replacement": false,
    "production_mutation": false,
    "calibration_refit": false,
    "platt_scaling": false,
    "isotonic_scaling": false,
    "score_transform_refit": false,
    "live_api_calls": 0,
    "paid_api_calls": 0,
    "canonical_rows_modified": false,
    "outcome_rows_modified": false,
    "p83e_mapping_modified": false,
    "source_artifacts_modified": false,
    "status": "PASSED"
  },
  "governance_all_pass": true,
  "paper_only": true,
  "diagnostic_only": true,
  "production_ready": false,
  "real_bet_allowed": false,
  "recommendation_allowed": false,
  "product_surface_allowed": false
}